zap_schema/__init__.py
zap_schema/agent_consensus.py
zap_schema/client.py
zap_schema/config.py
zap_schema/crypto.py
zap_schema/error.py
zap_schema/gateway.py
zap_schema/identity.py
zap_schema/server.py
zap_schema-1.0.0.dist-info/METADATA
zap_schema-1.0.0.dist-info/WHEEL
zap_schema-1.0.0.dist-info/entry_points.txt
zap_schema-1.0.0.dist-info/RECORD
