Metadata-Version: 2.4
Name: zap-schema
Version: 1.0.0
Summary: ZAP - Zero-Copy Application Protocol for AI agent communication
Project-URL: Homepage, https://zap-protocol.github.io/zap
Project-URL: Documentation, https://zap-protocol.github.io/zap/docs
Project-URL: Repository, https://github.com/zap-protocol/zap
Author-email: Hanzo AI <dev@hanzo.ai>
License-Expression: MIT
Keywords: ai-agents,capnproto,mcp,protocol,rpc,zap
Classifier: Development Status :: 5 - Production/Stable
Classifier: Intended Audience :: Developers
Classifier: License :: OSI Approved :: MIT License
Classifier: Programming Language :: Python :: 3
Classifier: Programming Language :: Python :: 3.10
Classifier: Programming Language :: Python :: 3.11
Classifier: Programming Language :: Python :: 3.12
Classifier: Topic :: Software Development :: Libraries
Classifier: Topic :: System :: Networking
Requires-Python: >=3.10
Requires-Dist: anyio>=4.0
Requires-Dist: httpx>=0.27
Requires-Dist: pycapnp>=2.0.0
Provides-Extra: dev
Requires-Dist: mypy>=1.13; extra == 'dev'
Requires-Dist: pytest-asyncio>=0.24; extra == 'dev'
Requires-Dist: pytest-cov>=5.0; extra == 'dev'
Requires-Dist: pytest>=8.0; extra == 'dev'
Requires-Dist: ruff>=0.8; extra == 'dev'
